{
"hav5phbqzu4jsrul5m7uhzan":["apnews-world-rss","AP News (World)"],
"f2vkoe6mu7hyiyjxwwirkd5l":["bbcnews-world-rss","BBCNews (World)"],
"yycqm7uzpp5uagobc2pi4umy":["bbcnews-uk-rss","BBCNews (UK)"],
"vljgfzvjl3dkmjgsjmdoaidc":["bbcnews-br-bot-rss.adilson.net.br","BBC News Brasil (Não oficial)"],
"342nhmiytgkspq5chaszabo5":["dp0rss1","M."],
"kzkl2onyewbs7pehh2ellzcb":["g1-bot-rss.adilson.net.br","Notícias do G1 (Não oficial)"],
"4s5yz6vxl4dhdr72jbhr75pc":["guardian-world-rss","The Guardian (World)"],
"5ki4mxytbomckts2st45yotc":["hnrss.org","Hacker News RSS"],
"c3vjodthd5xpjdnzmlnmhfvc":["minnaparssinen","Minna Pärssinen"],
"g7qssjpz455wq4vtmpteq7z7":["reuters-world-rss","Reuters (World)"],
"qfdhsnw7b3mmei2eysfha3gd":["romane-rssl","Romane Roussel"],
"hyol3jhkrwy6vsyky5mfzwtw":["rss.coffee","Rob (RSS) 🛫 TwitchCon"],
"tbctrt4t54kzdxvw36dugopc":["rsspost","JRSS Post Robot"],
"xkvuhipg3halfpflnasmdxqs":["rsswolf","WOLF"],
"o4tewr4opucnha7kotifdkcz":"rsstrife",
"tev7omcbkeu2a5hqyzm4nflo":["rssec","RS Sec"],
"5wd6avhoul6kudyeallu24iv":["rssviana","Ronan Viana"],
"mmvdlp6y34rwuxmp6tkopskp":"rssrinivas",
"emslp3vbwajugdwrd5jsmmtz":"rssfc",
"u7ubsi5s36nsuppdwfmuwivm":["rssc","REAL Savage Cabbage"],
"3afagub6iqa56or4v6kwwlux":"rssstvns",
"3venhymnsuccejuoc6a7qiol":["rssk","rssk"],
"vtkirkr3uqm6tubukeq5cwfg":["rssl","rssl"],
"xie3lix5kdlwjlarxceu2xat":["rssnsxts","Pierre"],
"si6aqtr4hcowestmq6yhhat2":["rssk6","알"],
"sytdbezwdvvkm5efe3zgozvc":"rssnico",
"qbiggl474sg4jb2nebmxle5d":"rsska5416",
"2udo2skehhgqjfows35ctr2d":["ruanssleite","RSS"],
"taijhii3ld3cxjije3sunoen":["saevarhalldorsson","Sævar Halldórsson"],
"f732l5w2pvioydxj5axylxas":["sawy3rssky","Sawyer"],
"2xhac6jx4va6qllmk6uzcqvw":["scloire","Loire // RSS"],
"z5pxyumuta55af3vd2j3lpox":["solvi","Sölvi Halldórsson"],
"3edxyncrqn4slmbw3nlgsjyj":["stevenjmesser","steve.rss"],
"ypgitiwnofn7svowagbwaftj":["steam-wklytop-rss","Steam Bot"],
"gfvqmuf3upwcvcmyrvszmsmc":["olofpettersson","Olof PΞTTΞRSSON 🔮"]
}
