{
"cowq5byp3f2lctuuektsslae":["3rdcataclysm","3rdCataclysm"],
"djo2i53slp452lwzndhbp35u":"2ndcity3rdcoast",
"eruybt7bmweodksg2gtlzykj":["3rdculture","blah"],
"tagfe4hbqwc7egd5d3oqmbbx":"3rdculturekid",
"rgjsba3iybp4ond4bpo43j6o":["c4rdc4pt0r","아샤"],
"i2pj4gwxsbriel4zx2oj3rcz":["joan3rdcoast","Joan Stephenson"],
"p3vkp74atakpraprpqucxazr":["l0rdcaptaincom2","Pedron Niall"],
"jlg5pinbzratmyf5sulavfu5":["mihatrochael","Miha Trochael (🐲RDC6) #SaveHannibal"],
"6vtvzezcmfoz3xljb56wk723":["my53rdchoice","John Peabody-Brown"],
"wc4cdqyimxqzwy7ehfqrbmtn":"rdc",
"zyaokauyzzhhcqfme2slp7uu":"rdcbbi",
"twdiv455hxuwmjel66ptnxr3":["rdch","Remy Chavannes"],
"oqcglkq2cq4ol57s3sh5thkm":"rdcrd",
"sltshqbyi5jlwbjaynj2uvud":["rdcorona","Daniel Corona"],
"zqyx643qp52ruy626c4hspwn":["rdconnell","Ross Connell"],
"llnrmsnjpggd52hcybmrqizh":"rdcomics",
"wepltjue3ibluckj5bsv4ak6":["rdcmpse","mantis"],
"yjwoldf53bkyagy76puchs37":"rdccomics",
"viz33hvgwlv5l3spqoenz74h":"rdcowley",
"tnjfsww7kj7we7cju3qxwz37":["rdcisco","Rdcisco 🦴🦴💵"],
"preip2esodlumkt7ymxbkrnn":["thisisigorrdc","igor rdc 🌈"],
"4m4775izay2fbr674h2n32jw":"the3rdcharles",
"l7u5vtobbrwez66xgagpoupc":["the3rdconstant","The3rdConstant"]
}
