{
"szyvm7v3zl4bvd2aaeghbrq6":["93degree","D. Rojo"],
"mnifuhbwmqzzx3hl3fe37tve":["andreasroj","Andreas Roj "],
"3fqaxjevlbp62t2sy6zoiywj":["antoniorojascastro","Antonio Rojas Castro"],
"7544zy6p4osbopxwxvrfp5vz":["aperezrojas","Andrés Pérez-Rojas, PhD"],
"5tc5shxaekt35uzb3clgkswl":["aquidania","Dania Rojas"],
"g2b4capfjlyquhtynf2emwpc":["atatsu3roji","阿辰巳ろじ"],
"3gv6tvfbyzn2pdk4ndysmivo":["autitranstomboy","Mar Rojas"],
"tfpb4uj5prt3lm45ongpmkic":["azulrojo","Azul Rojo"],
"zev7ynxuynfmkk7duqzd3y2s":["blazziest","blaise rojas"],
"7sjdutjweqgpzkziopyviyq5":["bossremo","Orlando “Kike” Medina Rojas"],
"f3unq4vvzsitlomwrxd2oqkr":["bruma-roja","Uncle Sam"],
"udtoluw57od2sp7ljqftovda":["caminored","Camino Rojo"],
"o5qerirbjaoks6owkpsd6dxz":["cabezarojo","Cabeza rojo"],
"z4df3pqe3piw67knfkaxko22":["catalinarojo","Catalina Rojo"],
"yozmzrji3m7tqo3bxsgepon4":["carloselrojo","Carlos el Rojo"],
"xxaywcodgay4p3hpwm5iopxf":["cheeshroom","Paula Rojas"],
"fcyelebz2xmqjya36nhdjwif":["corrinerojas","Corrine Rojas"],
"wc5kf5rlkbmv4ud52xzg5b5b":["crojas82","Christian Rojas"],
"4tblqpl7mmnlm3zlvxqg67be":["cruzrojarioja","Cruz Roja La Rioja"],
"f6kapvpglovvcckhjmbype4s":["davidrojas1006","David Rojas"],
"p4x72chlcp4oy4gem3g6okp6":["davidrojo","David Rojo"],
"tiehz6yckkqbqcbq6pcude5a":["docteeroh","Doc Theresa Rojas"],
"vo46ktkfi4ugygtkvoj4nl2c":["rojomarron","R."],
"kiumac5quwipdnn5oejy2x7n":["edubardo","Eduardo Rojas"],
"v7sokv35wty7ewis7jp7uqes":["eliab97","Eliab Rojas"],
"5dkqlgs4ibi6a6dylfpsbojg":["el49erfan","Aramen Rojas"],
"d6apthuh3sypgqhld6ippoby":["ellobitorojo","El Lobito Rojo"],
"ndfypbbw4s3tzxfq3hhxsdae":["emilianorojas","Emiliano Rojas"],
"u2wpxmvhh7s5amqvdxkzfc57":["extra.rojsmith.com","Roj Smith Extra 📷"],
"ew2kzrvvemzg2acfc5nxwcyr":["floofyrojo","Rojo"],
"sspjclm3v2ozz3ekk3guuq2e":["forjaroja","Forja Roja"],
"lalcsigwp5e3j3wdehsobvuk":["fundidoarojo","Fundido a rojo"],
"oybko2lyhqivjbufdprbgi72":["gorkarojo","Gorka Rojo"],
"ztrplr2pzifk3zvy2qkrkq4x":["gy164948","Rojhat Şahin"],
"raygyvfsru3d6cgl4fdx6kwp":["hatslife","azul rojo amarillo"],
"jf4fyfft6czqj5ikmoipksxz":["hexican","Hector Acosta Rojas. "],
"zppks7ejx5lodzpcvvjshvte":["hetavrojan","Hetav Rojan "],
"uaa4s6n6l35acem7iotqx4fu":["holymol3rojo","Bigfoot's bestie"],
"xwxmv5t5lrsyyz6cu2rahavi":["ingridrojasc","Ingrid Rojas Contreras"],
"625taqmxw5ysz3ccdlsfepva":["indrarojas","Indra Rojas"],
"l5buwd5acbmm6ohuqngtvsde":["izkrastyle","SyaaltRojas"],
"6w7t3mlnr2gk23tovma57lg5":["jacorojo","JacoRojo"],
"bg2f7s5dpylxcqftoznlbbkk":["jaderojas161","Jade Rojas"],
"cw6dueuusps2eybhwty672bv":["jedarova","Jesús Rojas"],
"tf5vmodcxrwebk346ulfmhiu":["jonrojas.com","Jon Rojas"],
"ox7gcs6bc7j6bl35mmeiepvo":["jotaerre3d","Jose Rojas"],
"f3yfqckkpfssgqv6t6vrtoek":["junioralvesade","Jurídico do Matias Rojas"],
"xbwblxszlm3w2swcrj67siy3":["justrojas","Justin Rojas"],
"3376lov7hbuvlxweddpu2hsk":["juanpablorojasv","Juan Pablo Rojas Viveros"],
"y6mmewsmllo42kydvhjdhd2j":["juanrojodesign","Juan Rojo Design "],
"cdhs5fpe65fi56dwf25pbtzn":["julie9","Julie Rojas"],
"sclssxmdpeykvzlynhs3drrq":["lamarianacosmica","Chef Mariana Rojas"],
"ag5t25ma34iy5eq5lakmfdse":["lg65","Luis Ernesto Rojas Gonzalez"],
"crrvph3lrdjhdl3jgupvic75":["lobachevscki","Julián Rojas Millán"],
"7zcfevdcqxpz6nhwbj7zzbzf":["luismirrojas","Luis Miguel Rojas"],
"epwynikmtnmcc46lmxlrkip5":["mariorojas","Mario Rojas"],
"vfm7r56vydtbcm5wrhaxrhqj":["martinrojas.dev","Martin Rojas"],
"6twaqpbc25hx4ahb6wsp4o6k":["markrojas","mark rojas"],
"7vw2hgmlspsa2zgf5gxm4nrb":["martinrojas","Martin Rojas "],
"rg54x7n3pbnew3snjnhwbtm3":["misteriorojo","Misterio Rojo"],
"lytb77kphdc42uqz4uvmwq6d":["montholr7","Man Monthol Rojumnong"],
"lc3qwxzokp7ccpisd7635gdj":["narizroja","NarizRoja"],
"tnahetd5clkonvv6ko4sh2su":["nadiaperezrojas","Nadia Pérez Rojas"],
"z2xvdtslk4n5q7vm24r27hkm":["nekrozero","Fernando Rojo"],
"ohibbzj53ycplpaiaaof3kol":["nickrojasvo","Nick Rojas"],
"cewffwufo3niemucmvsbqvnv":["nrojahn","Noah Rojahn"],
"b2mqou3kfw42u72g3ogm7tq7":["odile","Roja "],
"3j5x7cnptkr2vbyaadoyy44y":["ojo-rojo","👁️j👁️ Rojo"],
"b7x6y7p5nxbcxjwajugw3il7":["orquidearoja","Orquídea roja 🔻🌺♀️🩺"],
"pf662aovebmcjywfuqofwoz6":["panoco","¡Cuánto rojo!"],
"olxephypnssztfqlvtkfwavx":["patriciorojas","Patricio Rojas"],
"gjubo547e43prf7yxr6v2kn6":["palolili23","Paloma Rojas-Saunero"],
"7b2mscgtf5nypehbkkt5fkko":["patriciagarciarojo","Patricia García-Rojo"],
"4voh2brxbf7ca7q42fj3ims4":["pedrithor","Pedro D. Rojas 𒉭"],
"zffsnbbdtmbeygyqteac5oyr":["pelosdelbronx","Daniel Rojas Gonzalez"],
"tpc5vipmb5hgty43spgse7jq":["r0j1n","Rojin"],
"jo6q4awylui4cde6smgal4sp":["r0kh","Rojan Khanipour "],
"pjyilbotumv7vlgyrarqegxg":["remerasrojas","Remeras Rojas - Morimos por Star Trek"],
"nxeyoezazg2534vaiyj6i32r":["redreoja4","RedRoja"],
"lpb2jtlpw573ujsbb7xohe7b":["reysaurus","Luisa F. Rojas"],
"eh4ixfl36ls7rfoaetokbxjq":["rjnskl","Mira Rojanasakul"],
"hc4qizd5obheg2gqdwr5shy3":["rojina","Rojina"],
"mbdwxarz4xvmjlnotzf42fmv":["rojohi","Robbie"],
"miov5fifn2o2zd7mw42woida":["rojiura","＊𝕣𝕠𝕛𝕚𝕦𝕣𝕒＊"],
"xya62pe6pkvphkogar45ufqb":["rojoynegro.org","Rojo y Negro Records 🇵🇷"],
"yipda5vookixzw7z24gi22ma":["rojoaventuras","RoJo Aventuras"],
"zvhenux7dl6fllxoaghbdmbi":["roj","Tavroso"],
"n7557jkb5nmwvr6qzxm4qc2h":["rojoroach","RoJoRoach"],
"4xlw3xu6ibnows3cl7vu7vf6":["rojin","Rojin✨"],
"6zk277jekbdaxhuz7y6gjkbc":["rojohen","Uncle Roger"],
"l4bhbepkmlhx5buvsu3thdyu":["roj.as","Peter Rojas"],
"x2xqohunakbslx3ljt6gky2f":"rojo",
"jju53pxckr7xzvkdskz4xyfr":["rojinh777","Rojinh "],
"cekoaa42gwz6pjp3zit5lse6":"rojoto",
"tglygr45iud4wmc6prfor35j":["rojinhastam","Rojin"],
"xmc5jxp7l5qcahrl6r5weesc":["rojdaatatoprak","Rojda Atatoprak"],
"oh2inefpm6h76x3nfgbnz3lv":["rojinta","لوج"],
"5imdy5ejaljb2mkrhwaeqrn7":["rojan","🥹"],
"sac3xgvakt7p2lu546o3ealt":["rojper","Dra. Deolhama Bezerra"],
"tvfakngld6yzckyukp72cwym":["rojim","روجیم"],
"gcuibj5yq7ny56osqeua4zmv":["rojpak","Roja pakzad"],
"6brkh5e465r326gukx66a5il":"rojerwilko",
"grhjrgeayskxpw4zf4yyatht":["rojhelat","Rojhelat - ڕۆژهەڵات"],
"2kxgsgibtpwflcaaxzoutlkr":"rojones",
"qsvvhfagqau7k3gqk5cybjne":"rojhan",
"6zy75dp4cagtntaxdhuccn5r":["roje","Rosé"],
"xqvbkn7ujhaeszred7265xeg":["rojerpaw","kitty meister"],
"hum4i3qh2co7xau2dqvuv6ei":["rojoplatano","Rojoplatano"],
"xnnnj5oztdvbwbbqu7nmrq7y":["rojitas","Ashley Crystal Rojas "],
"o2366qybpk7ywvl6gnzfaq7f":["rojdaozcan","Rojda Ozcan"],
"rv6te6qjimsefjxzrlxuokcs":["rojolimar","Clarice Cobike"],
"lnesilfhynquelvpp4k3u7l3":["rojo10","Rob"],
"jnpwsdvzkxar47zjnvowdeyg":["rojakob","Roland Jakob"],
"wmmynzz6olyqmfcolmupe2sb":["rojj","roger"],
"qfgdm5juqquhhkad3ateizda":"rojiten",
"ufu3sptzimxkwjeex72nrvbp":["rojas","Eric Rojas"],
"uqfespo7sly6r2z6i6hwu7lg":["rojoroo","RedRooBoi"],
"cm2oyc77p3yy22pgclycehoi":["rojbas","roj baş"],
"6fadss2h6bhweed5yizf3jzk":"rojda",
"3oneglwafoyj3lj7mm7x2mgr":["rojeger","Rolf Jeger"],
"kzoonvmar3dwm35mifd76wpo":"rojardino",
"mgpr2uvp6evx45co7o3zqgds":["rojiblanco","André Kahle"],
"v6ulhooihkhxcq3bbjzmrrur":"rojonme",
"jdke7ahepfocuvwue2thf4by":["rojitojackal","Tata Rojito"],
"zuxld7i33crzk4kwlirasap7":["rojava","Kurdistan"],
"rxfbgd64drk5f3t5anqylgfx":["rojomosca","Rojomosca"],
"4j3t744uyo524j4kqzg44m3t":["rojsmith.com","Roj Smith 📷"],
"hp3ix44ghkx4zki4twpsuefd":["rojparody","Roj (Parody)"],
"23p5d5lp3tmab4mp55jnna2s":["rojo-x","Rojo x "],
"o3ruqdt7i7hbcrfi3txrtyud":"rojorojo",
"uvmi24ike6tpqgmoylwrxpbm":["rojopirata","Rojo "],
"xvgnp4vi77k2xe7r6apjdyte":["rojavakommitteerna.com","Rojavakommittéerna"],
"3horkzk5n7wdqdyn7f2st7zs":["rojofoxxo","Jazzi"],
"d3flosn2txnbewtuwgpyarak":["rojoarts","☆ Rojo ☆"],
"jpji57uacnvqpl5fdvrnte4q":["roji","Roji Tanner"],
"q7uokumayywwh2dem7tkcubm":"rojasazules",
"2njtzkudvjzxhimgabvs2mab":"rojoste",
"5li6qs2fapcha7lytx5nuni5":["robertorojas97","Roberto Rojas "],
"wr2jndwnsddzn6yl4xfft5on":["rojeviy","Рожеве психопатко 🏳️‍🌈🇺🇦"],
"a4kbnmykechqxhmjygy2g5je":["rojapiojosa","La Paula Real"],
"edpkcgiua2lfoghslathescf":"rojee",
"dnu54balbbpo6v4e3vg3lwjv":"rojjack",
"nwcebpbm4vwiisfj4lbsf2ei":"rojojojo",
"nlcauw3umgx5cq3gblirchjo":["rojiya","Roji 🎀"],
"zv6e37losj6c3yoqt3heuavw":["rojaru","Rojaru"],
"xly2q2clyv7jzxpolzmdbloh":"roja",
"yfdbjwqo4ymsssuaczbttp7q":["rojinfo","Rojinfo"],
"xqpi7wah7dxuxb6cuowaalb6":["rojapalpelo","Rojapalpelo"],
"rwvht3yut2yt3oda66madr56":"rojibeans19",
"vmanwulfahi4mtalevvqwnko":"rojoneon",
"cm3yt5fmprc6w4jndyzwyx52":"rojocomo",
"e3xz45l66mnokmjk4av62pbl":"rojivalo",
"mdezn73zpo4sittwmdwzb4nz":"rojoleon",
"2dx6vcdvg22bo2gwo2mhpun7":["rojosier","Efe"],
"a7rko6z6j457y2vj2re6wxwx":"rojoengeigakkai",
"6gjefmiz6ymxdl63wzbjjxv7":["rojulian","Rowan Steininger"],
"2zjf654ns54ldyao5orweg6s":["rojistecks","ろじてっく"],
"ajokhwrcngm36ixvwsvsphd5":"rojinv",
"p6cq6kqvdltyqi5qfhbqng2d":"rojema",
"24vgmesz66uclyrafhb34qeh":["rojodos2","Jose M. Juliá"],
"6egz7aapgooylhwvajuzhgfx":"rojnin",
"zblmtt72tjqnfi4aiy3c2m6r":["rojoclick","Mr Ro-Jo "],
"5qujylueyi2nmhzpfwytpucp":"rojinegra",
"rvaz5p4cua5p6iq4faivf4m2":["rojos4","Blue Sargent"],
"dm5djj4wsvft3h5gf5kyhyu6":["rojja6","VR Rojja"],
"wbmdmj6f46qomm2qanew54dd":["rojo015","Andrea🦄❄️"],
"jsklcuzyxe7lyl6txgap35hy":["rojobutsfw","Rojo?"],
"hewlkb6l4y54ebjpoifct7s3":["rojo7500","Rojo7500"],
"ft57uc6seuhw2ol63msf5y7i":"rojodelmal",
"6jfbuboekfu7po7eb4oneh5t":"rojack",
"nalol7n52ovt6xdjhkkmisdm":["rustyroj","Rusty Roj "],
"lpnnt5ugahcdw26wl4ya2xr7":["sabinerojko","SabineRojko "],
"evc7f5xueqblnh5oshrfk7nb":["seniormanager","Pedro Rojas"],
"yk45rfhow2e6qy6bm3ww73qw":["simsimma","Rojo."],
"lfjdyj3qphkcvr77laajngl7":["sor","روژ/Roj"],
"jf2ntodfq5nt2qtif33yzdhj":["solvermelho","Camarada Rojo 📕"],
"5rnw2jcwhyvui7fzslhes3lz":["susanrojas","susan rojas"],
"zq33unmqotbcpxyflzgp3kyl":["supinefox","el zorro rojo 🦊"],
"d44ztagrnxrp2neq3zrwrvmi":["svanir","Sol Rojo"],
"bqyli2agpvm3swjnkazfibbf":["tabularojo","Tabula Rojo"],
"e55xlexwghbx2emyfivt3f4p":["takorojo","Tako Rojo"],
"wvhtjbxasuhpibq6rqxkd3lh":["tcita","Tricia Rojo Bushnell"],
"t64jqj24ee3yyftet7y3s2sa":["tigrerojo01","Tigre rojo_01"],
"ailr3g6qheudjydzf4tjztcm":["toadheart","Rojbaş 𓆏"],
"b4mzwkfp6urvr7vo5cxrr334":["trelayne","Rojan Seth"],
"d433o6c356ejefthchuixtvk":["unairojo","Unai Rojo"],
"2l5qq7os5gakxotoicce3saj":["werewolfboyfriend","Lobo Rojas!"],
"vcaazxliofcvpbvwl7g6xsj3":["willrojo","Will Rojo"],
"foku5ai7rm4r7mkzkws6jxxl":["xn--d1alsl.xn--p1acf","Roj"],
"mazioj3yoomwg53acdxzxuat":["yopispico","El rojo del pelo azul"],
"grarcgn76grbyq3rvrp5ebro":["capitana40k","Señora mayor muy roja 🇯🇴♀️🏳️‍🌈🔻"]
}
