{
"v3662a5cmbz7vqfy37sxwcle":["aliceroques","Alice Roques"],
"ffefxbqczpzmawzu6b5hlx4q":"antoine-roquentin",
"gzvcg3kl75mil7u4dwqzfwkj":["dexint","Roque"],
"sygjf2dz7kejm2er66slgmey":["eroquegut","Ernesto Roque-Gutierrez"],
"7wvzit32doyckfzyc2t7akrr":["eulucasroque","Lucas Roque"],
"2cgrtw4yto7zwhzvix2nwz66":["fenixrisingxl21","Cisco Roque III"],
"3y3dvlu5mgdcfpvff24cyuyg":["gilproque.strangerverso.com","Gilberto Roque"],
"xpghclks37e5y4qm2kbo736a":["hawk","roque do povão"],
"2wpccaplyqzzlz3raproskud":["imposture","François Roque"],
"3kn4a2cainict74o5eskotts":["inqualia","Paul Roquet"],
"sisp3vaaeirvpkplxiu5jgdk":["iuroquetas","IU Roquetas"],
"y7dzwkqmiuaolvlnkw2lfycq":["katielaroque","Katie LaRoque"],
"zzgbpnmwkxxy7fi3hree744t":["krapmissile","poop roquette"],
"a45s4yq5v3leeydlljfcdwla":["lariroquini","Lari Roquini"],
"cdpo4tvrw2dzh4jppwhpocng":["logarythm","J-Roq"],
"cv3cuqrjw53tin7hbxa5i5kj":["luizroque","Luiz Roque 🏷📖"],
"yqsginwqkaimruqhqu77ewkk":["lyraa","Roquentin"],
"6xcafiqdzd7svefxhrchlw5n":["moniqueroquette","Monique & Roquette"],
"umykjsztudupi4zk7iemvqap":["mroque","Roque"],
"yq4r5xvbloxw7zlnfecsofmu":["noemieroques","Noémie Roques"],
"gze65hy2zdzja5t3mdbwjdih":["prataroque","Miguel Prata Roque"],
"u6it7zl2be7hg2h2v63qiw6t":["pyetrha","eu sou pyetrha e gosto de roque"],
"ewtv6rr5y4x5cxnqm7wldoro":["reageroqueiro","Reage Roqueiro (Rafael)"],
"uvmkntbuk6gz6gjolszysz66":["ritaroque","Rita Roque"],
"5dp5usdfxgtwxea2rovxg63k":["roque","☭ Comunista de iphone "],
"7wbneyjoioh54jn5xz3mgfkw":["roqin","Robin 🐦"],
"nwinjfzock3cx4dpdqahkgud":["roq11","Jules Winter"],
"qvndcvc4rcvbufq7dfo5wl6l":["roquefang","Roquefang at a Blue Sky"],
"xapxmyprxio543ox23vr26yi":["roquefortandquasar","Roquefort & Quasar"],
"efmwsxfzma3ou4cl5sqtrf45":"roquemadam",
"6uvmjhmr2qiqhzv36uhbqoak":"roquefreitas",
"2l7phhcsrer7pchxmsjdrvdq":["roquini","roquini"],
"yjaqdwgwrunibqnl6u3iceag":["roqayah","roqayah"],
"gy67lcyzybyzfdna3wms7da2":["roqueen","Roisin "],
"etbvnkf53z4nxtg7cwz3fifa":["roqkrcu","모찌"],
"zywrnetxb4tq4v6nj6nhup3v":["roquissas","roqs"],
"44ne4h3ribxurcguk7uq5xyr":"roqueroroger",
"5rarnruceskwhgjzqvz5kcgx":["roquemn","Roque Marques"],
"b7zdpgup5um2s2m7bn7qi4tu":"roquebono",
"5wsnmaylpxmaurj7q6blygwr":["roquerural","Roque"],
"lpycir2lpoqdbl325bu6wlz7":["roquitoqui","RT"],
"cbkpapdweg2o7ararckre52g":["roqdrummer","Roqdrummer"],
"gkjx5k4hryw2idh6nuup5t2l":["roquefore","Кіберкозак Олекса"],
"scj5qu4wz5l5wnskkxljoz3e":["roqqen","róqi"],
"6zdg3szqwftuxgve7regtix7":["roquemapache","Roque Mapache"],
"v32ez5htwo36sneod5q462tb":["roqqatz","weachers "],
"gp2qgsatnayxhnf4ge3ednh5":"roquestrew",
"jtnrmokk2u4tmjgbozd2xorm":["roqueandrolle","Amelia"],
"ahra42xawkhxr62haykig6m6":["roqyhawy","Hawy"],
"vmyrujzb6dujfkyalgcb7iwg":["roqzee","roqzee"],
"nngm3rq4ase7tpuojyaclps3":"roquej",
"en2hk7ztglso2ceuvulsvxd6":["roqaby","Gabkawa"],
"knguwxla7ac6bgihca2tz5cq":["roqqus","roqqus."],
"qq2s6s3h5crglxjvme3zour4":"roq4",
"5uot5zlmnhswsgpvth5ayult":["roquepoarr","meifius"],
"7hfh3rhaubhtret2p2qhpvrf":"roqueh",
"huclnc6fvycawh53rpe2cb7c":["roquida","Fred ten Kley"],
"urhftbbf7mpste757iezhjxw":"roquefortmaximus",
"3x5gna7r4foqb3gklfvfjeri":"roquefort",
"v3pf6ghiby4l6lj2szpkwq3e":["roq","DUMFAYCE"],
"jcl3il5mwdrc74cimweeb6w7":"roqz",
"he34tpwbmp4efeehgveazhj7":"roquea",
"iexei6m26hq6taofg3kvxgu2":"roquetansky",
"v6ynqacbcfsjy6rndeck2bur":["roque461","Roque461"],
"t7bd76nae3p7cummx2gtgayb":["rybat","Roqeeb Adedeji"],
"q733nwow7suql2huuemrkrkv":["sophieroques","Sophie Roques "],
"qswod3m62ho572ih76bvmx7b":["srq","Simon Roquette"],
"zhb7sulsdplha6iibmay6735":["tatiroque","Tatiana Roque"],
"xlkvtkkhsgbtu5wcuh26ypll":["thaisroque","Thais Roque"],
"pevhojgwzj5kiwonpfsoaa7r":["tilrq","Til Roquette"],
"thw6owxnaq6b6u2qknhkycuk":["velascorodrigo","Roque Coyote"],
"dap3gxmmusftvwjxbidiv5hg":["veraroquette","Vera Roquette"],
"qx5d5xac37bshkj5mv6y3ogy":["wivison","Wivison Roque"]
}
