{
"jkjfnzzyq4ofj5f3pcgwgkf5":["alianzartp","AlianzaRTP"],
"ts4lwsro5v7jefpcyfaeru2o":["ratapell","rtpllll"],
"hdsryvihrm4ilxfzc76i4tku":["rtparty","Rosie T / rtparty"],
"eeqw4s3khmbjtu56ypqjds6j":["rtpout","RTPout"],
"43ag6gwqz3d2q36gyp5r2cxo":"rtphilip",
"m3ijxws5af2o5af36umkosmv":["rtp","golden horde ombudsman "],
"avoihq3hp5jkp3vlofu4rhsc":"rtpete",
"bdaypoqyslo5owmirv3mitbc":"rtpguy82",
"fpapijqncglwj4gseylwpve4":["rtpedersen","Rasmus T Pedersen"],
"brqnv7cqinpi3x4k2fs5jfsw":["rtp360","john"],
"uvnpcvys6vy6feqegptvcpit":"rtpyagi",
"tpkqkdxqqehiejoodobloogl":["rtpg","Raphael"],
"ncnfrji7yac4hq5lijmclla2":["rtpprincess","RTP Princess"],
"c34f2qazuluwsdqlvn2x7vhn":["rtperson3","Rob Person"],
"hentrypy2mjvqgkyob6wuil3":["sh0rtpers0n","Bailey"]
}
