{
"mix2u4t64v6aee4wjnrpf6zl":["rpcreative","Rui Pinho Creative "],
"7ey54rpm352nw7ddfxfvhth7":["rpc","Gunther Bütidü"],
"2l2oen3khwdnixqab6nzvnqr":["rpch.io","Ryan Christensen"],
"qp2pjphzgknkutwhh7wp4cmz":["rpchaves","Rui Chaves"],
"feuzslh3iz7vxyqur5rpiqpd":["rpcauthor","Rachelle Paige Campbell "],
"b2w7wiveor7kamg2pms346wc":["rpct457","Ryan P. C. Trimble"],
"ddu5syfux46nczwpu33vj7nz":"rpc1929",
"rqaco3gvmxzdc2haydw4ouql":"rpcab",
"nzk4gln3lu6i27uhexfd6jnj":"rpc20",
"xpkknqvhap75vwbzwv4xhg2z":["rpc25","Ross Church"],
"tajekvxhk5euyswfmkxquonw":["rpcprotogen","Rpc"],
"oej2sip5sry5pigz2vfuzhob":"rpcx",
"sdkhrt5lvn6mwriefsmaxrzq":"rpcraft",
"5hz4ddx7rxmbbc3rmdu7byyn":["rpc732","Richard Caldarone"]
}
