{
"4mz25qvm2nqbywrwj3pknqk3":["apprepuff","puff 🔥 king of streamer rpf"],
"cyrahzrnm5wp3xkl5ans65jq":["dipl-rpfl","Dipl_Rpfl"],
"dxtwhjyprnpppqakniezliny":["it-rpfl","iT-Rpfl - #Justiz #Family #Nerd-Stuff"],
"yhshwp6j5sbuvzws7n35dioi":["rom.omg.lol","RPF"],
"szifjmok4r2s6g2v5xl4kd7f":["rpfdmopo","Eric Hofmann"],
"slguhdwtgzeeytxfomvdywpq":["rpfn","용"],
"d5occbkdujolk52bffgvfs4i":["rpf","Rúben P. Ferreira"],
"3rrfwmgrbznqrq6yh5vmgyv4":["rpflynn","Richard Flynn"],
"qp5on46wenb2okzkupkzixyf":["rpfcosta","Rui Costa"],
"fub4qlzuw234gxqwsxruvy3n":"rpfpfr",
"6nz533zwiikhdziqej3d4te7":"rpflamm"
}
