{
"b4ljvaqrqqz2ykb6hxan6mef":["almaotter","RPO the Jewels"],
"cevbljjo42jgcyjdbe3q6sdv":["art175etrpo1","Ex art. 175 aujourd’hui RPO1"],
"kvqxkk7namyws7tzi37fe3p2":["corporalolle","🇺🇦Tyttebærpoliti🇺🇦"],
"iqtqtooorbz7qyi7lt57q4js":["rpollien","Rob Pollien"],
"nbm5xm7vh5zaimhsnxfmjwti":["rpowell138","Ryan Powell"],
"qntrzgbv3xckwxlyyopufbff":["rpoprr","Heli"],
"rrjgft2g4aliwsvuicj2du73":["rporosheldon","Porosheldon_"],
"s7xfr6ck257oxwxazhivugvi":["rpocisv","Rodrigo Pérez Ortega"],
"ghsvikosmrozuh7jwhyizf7f":"rpobeirne",
"4wppg7dnqpoioklplodfvejg":["rportnoy","Ramiro Portnoy"],
"czngi3av5phpxpusfixkpgba":["rpo","Stichting Regionale Publieke Omroep"],
"d4y7bp75r4ixxe4jdng474ao":"rpohara",
"tob3zomwrpbs3xbgohuwoahj":"rpolishdo",
"hadr2xscwzvylkxg6qb5cefu":["rponciano","Renato Ponciano"],
"yc24odordyd2hltzd4ykgodn":"rpopovs",
"tdvgakjxrrlyqdbzldpjxww7":["rpodric","Rick"],
"j2shy6hvf6lumgtvjncj7huc":["rpminuteman314","RPoland"],
"zhvtacpinhjgskiuuknafsp6":["rpope","Radu Popescu"],
"4kl3cdurkrgy2s5y5jpktd4p":"rpowers",
"wgorqj46ngksuyunfpe2jwlz":["rporetsky","Rachel Poretsky"],
"ljkjxkf4quuwkpinuymrosym":["rpodonnell","Ryan P. O’Donnell"],
"kg4bwuvpyoogfxwnuz4vuuu3":"rpowell",
"62ab2yfimky42oocum6qgtxa":"rpopa",
"vi6fj7gdbk6meikywesljtwn":["rpower","Rachel"],
"7w6avqqde776t3wfb63gln7j":["rpobihach","Roman"],
"j3hi55dqprwegb362dxiwbll":"rpopp",
"xmi2hljqcno4idshgexpeylv":"rpowell-media",
"4yjdf4pmifdgpg4s6akkp7v3":["rponly","abby, bby."],
"tmct5wnntzcs7nklip5twx42":"rportnoy123",
"ewprw2qacpgdchvwrzpryu2m":["rpommerm","Ricardo Pommer Muñoz"],
"n4ihm2cqxwkuull4qbluvplq":["st4rpower","James M"]
}
